plato/__init__.py
plato/py.typed
plato/_generated/__init__.py
plato/_generated/client.py
plato/_generated/errors.py
plato/_generated/py.typed
plato/_generated/api/__init__.py
plato/_generated/api/v1/__init__.py
plato/_generated/api/v1/agent_artifacts/__init__.py
plato/_generated/api/v1/agent_artifacts/archive_agent_artifact.py
plato/_generated/api/v1/agent_artifacts/create_agent_artifact.py
plato/_generated/api/v1/agent_artifacts/get_agent_artifact_by_public_id.py
plato/_generated/api/v1/agent_artifacts/get_agent_artifacts.py
plato/_generated/api/v1/cluster/__init__.py
plato/_generated/api/v1/cluster/cleanup_stale_vms.py
plato/_generated/api/v1/cluster/get_dispatchers.py
plato/_generated/api/v1/cluster/get_nodes_status.py
plato/_generated/api/v1/cluster/get_snapshot_lineage.py
plato/_generated/api/v1/cluster/get_snapshots_status.py
plato/_generated/api/v1/cluster/pause_resume_dispatchers.py
plato/_generated/api/v1/cluster/prefetch_snapshot.py
plato/_generated/api/v1/env/__init__.py
plato/_generated/api/v1/env/backup.py
plato/_generated/api/v1/env/cleanup.py
plato/_generated/api/v1/env/close.py
plato/_generated/api/v1/env/close_async.py
plato/_generated/api/v1/env/create.py
plato/_generated/api/v1/env/create_batch.py
plato/_generated/api/v1/env/create_simulator.py
plato/_generated/api/v1/env/evaluate_session.py
plato/_generated/api/v1/env/generate_mutations.py
plato/_generated/api/v1/env/generate_mutations_single.py
plato/_generated/api/v1/env/get_active_session.py
plato/_generated/api/v1/env/get_app_sim_worker_info.py
plato/_generated/api/v1/env/get_cdp_url.py
plato/_generated/api/v1/env/get_flows.py
plato/_generated/api/v1/env/get_interface_worker_info.py
plato/_generated/api/v1/env/get_job_info.py
plato/_generated/api/v1/env/get_job_status.py
plato/_generated/api/v1/env/get_job_worker_info.py
plato/_generated/api/v1/env/get_proxy_url.py
plato/_generated/api/v1/env/get_public_url.py
plato/_generated/api/v1/env/get_simulator_by_name.py
plato_sdk_v2-2.8.3.dist-info/METADATA
plato_sdk_v2-2.8.3.dist-info/WHEEL
plato_sdk_v2-2.8.3.dist-info/entry_points.txt
plato_sdk_v2-2.8.3.dist-info/RECORD
