Metadata-Version: 2.4
Name: plato-sdk-v2
Version: 2.8.3
Summary: Python SDK for the Plato API
Author-email: Plato <support@plato.so>
License-Expression: MIT
Classifier: Development Status :: 4 - Beta
Classifier: Intended Audience :: Developers
Classifier: License :: OSI Approved :: MIT License
Classifier: Programming Language :: Python :: 3
Classifier: Programming Language :: Python :: 3.10
Classifier: Programming Language :: Python :: 3.11
Classifier: Programming Language :: Python :: 3.12
Classifier: Typing :: Typed
Requires-Python: <3.14,>=3.10
Requires-Dist: aiohttp>=3.8.0
Requires-Dist: cryptography>=43.0.0
Requires-Dist: datamodel-code-generator>=0.43.0
Requires-Dist: email-validator>=2.0.0
Requires-Dist: google-genai>=1.0.0
Requires-Dist: httpx>=0.25.0
Requires-Dist: jinja2>=3.1.0
Requires-Dist: openapi-pydantic>=0.5.1
Requires-Dist: opentelemetry-api>=1.20.0
Requires-Dist: opentelemetry-exporter-otlp-proto-http>=1.20.0
Requires-Dist: opentelemetry-sdk>=1.20.0
Requires-Dist: pydantic-settings>=2.12.0
Requires-Dist: pydantic>=2.0.0
Requires-Dist: python-dotenv>=1.2.1
Requires-Dist: pyyaml>=6.0
Requires-Dist: requests>=2.32.5
Requires-Dist: rich>=13.0.0
Requires-Dist: tenacity>=9.1.2
Requires-Dist: tomli>=2.0.0
Requires-Dist: typer>=0.9.0
Provides-Extra: db-cleanup
Requires-Dist: aiomysql>=0.2; extra == 'db-cleanup'
Requires-Dist: aiosqlite>=0.20; extra == 'db-cleanup'
Requires-Dist: asyncpg>=0.29; extra == 'db-cleanup'
Requires-Dist: sqlalchemy[asyncio]>=2.0; extra == 'db-cleanup'
Provides-Extra: dev
Requires-Dist: basedpyright>=1.18; extra == 'dev'
Requires-Dist: pytest-asyncio>=0.21; extra == 'dev'
Requires-Dist: pytest>=7.0; extra == 'dev'
Requires-Dist: ruff>=0.1; extra == 'dev'
